pdf_header_detector/__init__.py
pdf_header_detector/__main__.py
pdf_header_detector/cli.py
pdf_header_detector/detector.py
pdf_header_detector-1.0.0.dist-info/licenses/LICENSE.md
pdf_header_detector-1.0.0.dist-info/METADATA
pdf_header_detector-1.0.0.dist-info/WHEEL
pdf_header_detector-1.0.0.dist-info/entry_points.txt
pdf_header_detector-1.0.0.dist-info/top_level.txt
pdf_header_detector-1.0.0.dist-info/RECORD
